rest_framework_fine_permissions/__init__.py
rest_framework_fine_permissions/admin.py
rest_framework_fine_permissions/apps.py
rest_framework_fine_permissions/fields.py
rest_framework_fine_permissions/filters.py
rest_framework_fine_permissions/models.py
rest_framework_fine_permissions/permissions.py
rest_framework_fine_permissions/serializers.py
rest_framework_fine_permissions/urls.py
rest_framework_fine_permissions/utils.py
rest_framework_fine_permissions/views.py
rest_framework_fine_permissions/management/__init__.py
rest_framework_fine_permissions/management/commands/__init__.py
rest_framework_fine_permissions/management/commands/fine_permissions_dump.py
rest_framework_fine_permissions/management/commands/fine_permissions_load.py
rest_framework_fine_permissions/migrations/0001_initial.py
rest_framework_fine_permissions/migrations/0002_swappable_user.py
rest_framework_fine_permissions/migrations/__init__.py
rest_framework_fine_permissions/templates/admin/rest_framework_fine_permissions/userfieldpermissions/change_form.html
djangorestframework_fine_permissions-0.9.2.dist-info/LICENSE
djangorestframework_fine_permissions-0.9.2.dist-info/METADATA
djangorestframework_fine_permissions-0.9.2.dist-info/WHEEL
djangorestframework_fine_permissions-0.9.2.dist-info/top_level.txt
djangorestframework_fine_permissions-0.9.2.dist-info/RECORD
