Metadata-Version: 2.1
Name: djangorestframework-fine-permissions
Version: 0.9.2
Summary: Field level permissions for Django REST Framework
Home-page: https://github.com/unistra/django-rest-framework-fine-permissions
Author: dnum-dip-unistra
Author-email: dnum-dip@unistra.fr
Maintainer: dnum-dip-unistra
Maintainer-email: dnum-dip@unistra.fr
License: UNKNOWN
Download-URL: https://pypi.python.org/pypi/djangorestframework-fine-permissions
Keywords: django,REST,rest_framework,permissions
Platform: UNKNOWN
Classifier: Development Status :: 4 - Beta
Classifier: Environment :: Web Environment
Classifier: Framework :: Django
Classifier: Intended Audience :: Developers
Classifier: License :: OSI Approved :: GNU General Public License v2 (GPLv2)
Classifier: Programming Language :: Python :: 3.8
Classifier: Programming Language :: Python :: 3.9
Classifier: Programming Language :: Python :: 3.10
Classifier: Framework :: Django
Classifier: Framework :: Django :: 3.2
